crossclip/__init__.py
crossclip/absbackend.py
crossclip/clipboard.py
crossclip/gtkbackend.py
crossclip/qtbackend.py
crossclip/winbackend.py
crossclip/tests/__init__.py
crossclip/tests/clipboard_test.py
crossclip-0.2.2.dist-info/LICENSE
crossclip-0.2.2.dist-info/METADATA
crossclip-0.2.2.dist-info/WHEEL
crossclip-0.2.2.dist-info/top_level.txt
crossclip-0.2.2.dist-info/RECORD
