Metadata-Version: 2.1
Name: crossclip
Version: 0.2.2
Summary: A Cross Platform clipboard manager
Home-page: https://github.com/softwaresale/crossclip
Author: Charlie Sale
Author-email: softwaresale01@gmail.com
License: UNKNOWN
Platform: UNKNOWN
Classifier: Development Status :: 4 - Beta
Classifier: Intended Audience :: Developers
Classifier: Programming Language :: Python :: 3
Classifier: License :: OSI Approved :: GNU General Public License v3 (GPLv3)
Classifier: Operating System :: OS Independent
Classifier: Topic :: Software Development :: Libraries
Requires-Dist: Pillow
Provides-Extra: gtk
Requires-Dist: pygobject ; extra == 'gtk'
Provides-Extra: qt
Requires-Dist: PyQt5 ; extra == 'qt'
